{"includedArchiveIdentifiers":["MetalFFT"],"interfaceLanguages":{"swift":[{"children":[{"title":"Classes","type":"groupMarker"},{"children":[{"title":"Initializers","type":"groupMarker"},{"path":"\/documentation\/metalfft\/convolver\/init(kernel:fftsize:)","title":"init(kernel: [Float], fftSize: Int) throws","type":"init"},{"title":"Instance Properties","type":"groupMarker"},{"path":"\/documentation\/metalfft\/convolver\/blocksize","title":"let blockSize: Int","type":"property"},{"path":"\/documentation\/metalfft\/convolver\/hopsize","title":"let hopSize: Int","type":"property"},{"title":"Instance Methods","type":"groupMarker"},{"path":"\/documentation\/metalfft\/convolver\/apply(to:)","title":"func apply(to: [Float]) throws -> [Float]","type":"method"},{"title":"Type Methods","type":"groupMarker"},{"path":"\/documentation\/metalfft\/convolver\/recommendedfftsize(forkernelcount:)","title":"static func recommendedFFTSize(forKernelCount: Int) -> Int?","type":"method"}],"path":"\/documentation\/metalfft\/convolver","title":"Convolver","type":"class"},{"children":[{"title":"Initializers","type":"groupMarker"},{"path":"\/documentation\/metalfft\/correlator\/init(fftsize:)","title":"init(fftSize: Int) throws","type":"init"},{"title":"Instance Properties","type":"groupMarker"},{"path":"\/documentation\/metalfft\/correlator\/fftsize","title":"let fftSize: Int","type":"property"},{"title":"Instance Methods","type":"groupMarker"},{"path":"\/documentation\/metalfft\/correlator\/auto(_:)","title":"func auto([Float]) throws -> [Float]","type":"method"},{"path":"\/documentation\/metalfft\/correlator\/cross(_:_:)","title":"func cross([Float], [Float]) throws -> [Float]","type":"method"}],"path":"\/documentation\/metalfft\/correlator","title":"Correlator","type":"class"},{"children":[{"title":"Initializers","type":"groupMarker"},{"path":"\/documentation\/metalfft\/fftanalyzer\/init(size:samplerate:window:)","title":"init(size: Int, sampleRate: Double, window: WindowType) throws","type":"init"},{"title":"Instance Properties","type":"groupMarker"},{"path":"\/documentation\/metalfft\/fftanalyzer\/samplerate","title":"let sampleRate: Double","type":"property"},{"path":"\/documentation\/metalfft\/fftanalyzer\/size","title":"let size: Int","type":"property"},{"title":"Instance Methods","type":"groupMarker"},{"path":"\/documentation\/metalfft\/fftanalyzer\/analyze(_:)","title":"func analyze([Float]) throws -> AnalysisResult","type":"method"},{"path":"\/documentation\/metalfft\/fftanalyzer\/analyze(_:offset:)","title":"func analyze([Float], offset: Int) throws -> AnalysisResult","type":"method"}],"path":"\/documentation\/metalfft\/fftanalyzer","title":"FFTAnalyzer","type":"class"},{"children":[{"title":"Initializers","type":"groupMarker"},{"path":"\/documentation\/metalfft\/frequencytracker\/init(smoothingwindow:)","title":"init(smoothingWindow: Int)","type":"init"},{"title":"Instance Properties","type":"groupMarker"},{"path":"\/documentation\/metalfft\/frequencytracker\/smoothingwindow","title":"let smoothingWindow: Int","type":"property"},{"title":"Instance Methods","type":"groupMarker"},{"path":"\/documentation\/metalfft\/frequencytracker\/reset()","title":"func reset()","type":"method"},{"path":"\/documentation\/metalfft\/frequencytracker\/track(_:)","title":"func track(Float) -> Float","type":"method"}],"path":"\/documentation\/metalfft\/frequencytracker","title":"FrequencyTracker","type":"class"},{"children":[{"title":"Initializers","type":"groupMarker"},{"path":"\/documentation\/metalfft\/fusedconvolver\/init(kernel:fftsize:precision:)","title":"init(kernel: [Float], fftSize: Int, precision: FusedConvolver.Precision) throws","type":"init"},{"title":"Instance Properties","type":"groupMarker"},{"path":"\/documentation\/metalfft\/fusedconvolver\/hopsize","title":"let hopSize: Int","type":"property"},{"path":"\/documentation\/metalfft\/fusedconvolver\/kernellen","title":"let kernelLen: Int","type":"property"},{"path":"\/documentation\/metalfft\/fusedconvolver\/precision-swift.property","title":"let precision: FusedConvolver.Precision","type":"property"},{"title":"Instance Methods","type":"groupMarker"},{"path":"\/documentation\/metalfft\/fusedconvolver\/apply(to:)","title":"func apply(to: [Float]) throws -> [Float]","type":"method"},{"title":"Type Properties","type":"groupMarker"},{"path":"\/documentation\/metalfft\/fusedconvolver\/supportedsize","title":"static let supportedSize: Int","type":"property"},{"title":"Enumerations","type":"groupMarker"},{"children":[{"title":"Enumeration Cases","type":"groupMarker"},{"path":"\/documentation\/metalfft\/fusedconvolver\/precision-swift.enum\/float16mixed","title":"case float16Mixed","type":"case"},{"path":"\/documentation\/metalfft\/fusedconvolver\/precision-swift.enum\/float16pure","title":"case float16Pure","type":"case"},{"path":"\/documentation\/metalfft\/fusedconvolver\/precision-swift.enum\/float16storage","title":"case float16Storage","type":"case"},{"path":"\/documentation\/metalfft\/fusedconvolver\/precision-swift.enum\/float32","title":"case float32","type":"case"},{"title":"Default Implementations","type":"groupMarker"},{"children":[{"title":"Operators","type":"groupMarker"},{"path":"\/documentation\/metalfft\/fusedconvolver\/precision-swift.enum\/!=(_:_:)","title":"static func != (Self, Self) -> Bool","type":"op"}],"path":"\/documentation\/metalfft\/fusedconvolver\/precision-swift.enum\/equatable-implementations","title":"Equatable Implementations","type":"symbol"}],"path":"\/documentation\/metalfft\/fusedconvolver\/precision-swift.enum","title":"FusedConvolver.Precision","type":"enum"}],"path":"\/documentation\/metalfft\/fusedconvolver","title":"FusedConvolver","type":"class"},{"children":[{"title":"Initializers","type":"groupMarker"},{"path":"\/documentation\/metalfft\/metalfft\/init(size:)","title":"init(size: Int) throws","type":"init"},{"title":"Instance Properties","type":"groupMarker"},{"path":"\/documentation\/metalfft\/metalfft\/size","title":"let size: Int","type":"property"},{"title":"Instance Methods","type":"groupMarker"},{"path":"\/documentation\/metalfft\/metalfft\/forward(_:)","title":"func forward([SIMD2<Float>]) throws -> [SIMD2<Float>]","type":"method"},{"path":"\/documentation\/metalfft\/metalfft\/forward(batch:)","title":"func forward(batch: [[SIMD2<Float>]]) throws -> [[SIMD2<Float>]]","type":"method"},{"path":"\/documentation\/metalfft\/metalfft\/forward(input:output:)","title":"func forward(input: UnsafeBufferPointer<SIMD2<Float>>, output: inout [SIMD2<Float>]) throws","type":"method"},{"path":"\/documentation\/metalfft\/metalfft\/inverse(_:)","title":"func inverse([SIMD2<Float>]) throws -> [SIMD2<Float>]","type":"method"}],"path":"\/documentation\/metalfft\/metalfft","title":"MetalFFT","type":"class"},{"children":[{"title":"Initializers","type":"groupMarker"},{"path":"\/documentation\/metalfft\/multichannelfft\/init(channels:size:)","title":"init(channels: Int, size: Int) throws","type":"init"},{"title":"Instance Properties","type":"groupMarker"},{"path":"\/documentation\/metalfft\/multichannelfft\/channels","title":"let channels: Int","type":"property"},{"path":"\/documentation\/metalfft\/multichannelfft\/size","title":"let size: Int","type":"property"},{"title":"Instance Methods","type":"groupMarker"},{"path":"\/documentation\/metalfft\/multichannelfft\/forward(_:)","title":"func forward([[SIMD2<Float>]]) throws -> [[SIMD2<Float>]]","type":"method"},{"path":"\/documentation\/metalfft\/multichannelfft\/inverse(_:)","title":"func inverse([[SIMD2<Float>]]) throws -> [[SIMD2<Float>]]","type":"method"}],"path":"\/documentation\/metalfft\/multichannelfft","title":"MultiChannelFFT","type":"class"},{"children":[{"title":"Initializers","type":"groupMarker"},{"path":"\/documentation\/metalfft\/onsetdetector\/init(samplerate:fftsize:hopsize:)","title":"init(sampleRate: Double, fftSize: Int, hopSize: Int) throws","type":"init"},{"title":"Instance Properties","type":"groupMarker"},{"path":"\/documentation\/metalfft\/onsetdetector\/fftsize","title":"let fftSize: Int","type":"property"},{"path":"\/documentation\/metalfft\/onsetdetector\/hopsize","title":"let hopSize: Int","type":"property"},{"path":"\/documentation\/metalfft\/onsetdetector\/ispeak","title":"var isPeak: Bool","type":"property"},{"path":"\/documentation\/metalfft\/onsetdetector\/onsets","title":"var onsets: [Double]","type":"property"},{"path":"\/documentation\/metalfft\/onsetdetector\/samplerate","title":"let sampleRate: Double","type":"property"},{"title":"Instance Methods","type":"groupMarker"},{"path":"\/documentation\/metalfft\/onsetdetector\/feed(_:)","title":"func feed([Float]) throws","type":"method"},{"path":"\/documentation\/metalfft\/onsetdetector\/reset()","title":"func reset()","type":"method"}],"path":"\/documentation\/metalfft\/onsetdetector","title":"OnsetDetector","type":"class"},{"children":[{"title":"Initializers","type":"groupMarker"},{"path":"\/documentation\/metalfft\/stft\/init(fftsize:hopsize:window:samplerate:)","title":"init(fftSize: Int, hopSize: Int, window: WindowType, sampleRate: Double) throws","type":"init"},{"title":"Instance Properties","type":"groupMarker"},{"path":"\/documentation\/metalfft\/stft\/fftsize","title":"let fftSize: Int","type":"property"},{"path":"\/documentation\/metalfft\/stft\/hopsize","title":"let hopSize: Int","type":"property"},{"path":"\/documentation\/metalfft\/stft\/samplerate","title":"let sampleRate: Double","type":"property"},{"title":"Instance Methods","type":"groupMarker"},{"path":"\/documentation\/metalfft\/stft\/analyze(_:)","title":"func analyze([Float]) throws -> [STFTFrame]","type":"method"},{"path":"\/documentation\/metalfft\/stft\/binfrequency(_:)","title":"func binFrequency(Int) -> Double","type":"method"},{"path":"\/documentation\/metalfft\/stft\/framecount(for:)","title":"func frameCount(for: Int) -> Int","type":"method"},{"path":"\/documentation\/metalfft\/stft\/frametime(_:)","title":"func frameTime(Int) -> Double","type":"method"},{"path":"\/documentation\/metalfft\/stft\/spectrogram(_:)","title":"func spectrogram([Float]) throws -> [[Float]]","type":"method"}],"path":"\/documentation\/metalfft\/stft","title":"STFT","type":"class"},{"title":"Structures","type":"groupMarker"},{"children":[{"title":"Instance Properties","type":"groupMarker"},{"path":"\/documentation\/metalfft\/analysisresult\/complex","title":"let complex: [SIMD2<Float>]","type":"property"},{"path":"\/documentation\/metalfft\/analysisresult\/dominantfreq","title":"var dominantFreq: Float?","type":"property"},{"path":"\/documentation\/metalfft\/analysisresult\/dominantnote","title":"var dominantNote: (name: String, octave: Int)?","type":"property"},{"path":"\/documentation\/metalfft\/analysisresult\/fftsize","title":"let fftSize: Int","type":"property"},{"path":"\/documentation\/metalfft\/analysisresult\/isnoise","title":"var isNoise: Bool","type":"property"},{"path":"\/documentation\/metalfft\/analysisresult\/magnitudes","title":"var magnitudes: [Float]","type":"property"},{"path":"\/documentation\/metalfft\/analysisresult\/magnitudesdb","title":"var magnitudesDB: [Float]","type":"property"},{"path":"\/documentation\/metalfft\/analysisresult\/phase","title":"var phase: [Float]","type":"property"},{"path":"\/documentation\/metalfft\/analysisresult\/rms","title":"var rms: Float","type":"property"},{"path":"\/documentation\/metalfft\/analysisresult\/samplerate","title":"let sampleRate: Double","type":"property"},{"title":"Instance Methods","type":"groupMarker"},{"path":"\/documentation\/metalfft\/analysisresult\/binfrequency(_:)","title":"func binFrequency(Int) -> Double","type":"method"}],"path":"\/documentation\/metalfft\/analysisresult","title":"AnalysisResult","type":"struct"},{"children":[{"title":"Instance Properties","type":"groupMarker"},{"path":"\/documentation\/metalfft\/bandenergy\/air","title":"let air: Float","type":"property"},{"path":"\/documentation\/metalfft\/bandenergy\/all","title":"var all: [(name: String, energy: Float)]","type":"property"},{"path":"\/documentation\/metalfft\/bandenergy\/bass","title":"let bass: Float","type":"property"},{"path":"\/documentation\/metalfft\/bandenergy\/low","title":"let low: Float","type":"property"},{"path":"\/documentation\/metalfft\/bandenergy\/mid","title":"let mid: Float","type":"property"},{"path":"\/documentation\/metalfft\/bandenergy\/sub","title":"let sub: Float","type":"property"},{"path":"\/documentation\/metalfft\/bandenergy\/total","title":"var total: Float","type":"property"},{"path":"\/documentation\/metalfft\/bandenergy\/upper","title":"let upper: Float","type":"property"}],"path":"\/documentation\/metalfft\/bandenergy","title":"BandEnergy","type":"struct"},{"children":[{"title":"Instance Properties","type":"groupMarker"},{"path":"\/documentation\/metalfft\/crossspectralresult\/channels","title":"let channels: Int","type":"property"},{"path":"\/documentation\/metalfft\/crossspectralresult\/coherence","title":"let coherence: [[Float]]","type":"property"},{"path":"\/documentation\/metalfft\/crossspectralresult\/crossspectra","title":"let crossSpectra: [[SIMD2<Float>]]","type":"property"},{"path":"\/documentation\/metalfft\/crossspectralresult\/fftsize","title":"let fftSize: Int","type":"property"},{"path":"\/documentation\/metalfft\/crossspectralresult\/paircount","title":"var pairCount: Int","type":"property"},{"path":"\/documentation\/metalfft\/crossspectralresult\/power","title":"let power: [[Float]]","type":"property"},{"title":"Instance Methods","type":"groupMarker"},{"path":"\/documentation\/metalfft\/crossspectralresult\/pairindex(_:_:)","title":"func pairIndex(Int, Int) -> Int","type":"method"}],"path":"\/documentation\/metalfft\/crossspectralresult","title":"CrossSpectralResult","type":"struct"},{"children":[{"title":"Initializers","type":"groupMarker"},{"path":"\/documentation\/metalfft\/frequencybands\/init(samplerate:fftsize:)","title":"init(sampleRate: Double, fftSize: Int)","type":"init"},{"title":"Instance Properties","type":"groupMarker"},{"path":"\/documentation\/metalfft\/frequencybands\/fftsize","title":"let fftSize: Int","type":"property"},{"path":"\/documentation\/metalfft\/frequencybands\/samplerate","title":"let sampleRate: Double","type":"property"},{"title":"Instance Methods","type":"groupMarker"},{"path":"\/documentation\/metalfft\/frequencybands\/analyze(_:)","title":"func analyze([Float]) -> BandEnergy","type":"method"},{"path":"\/documentation\/metalfft\/frequencybands\/analyzenormalized(_:)","title":"func analyzeNormalized([Float]) -> BandEnergy","type":"method"}],"path":"\/documentation\/metalfft\/frequencybands","title":"FrequencyBands","type":"struct"},{"children":[{"title":"Instance Properties","type":"groupMarker"},{"path":"\/documentation\/metalfft\/stftframe\/complex","title":"let complex: [SIMD2<Float>]","type":"property"},{"path":"\/documentation\/metalfft\/stftframe\/magnitudes","title":"let magnitudes: [Float]","type":"property"},{"path":"\/documentation\/metalfft\/stftframe\/magnitudesdb","title":"var magnitudesDB: [Float]","type":"property"},{"path":"\/documentation\/metalfft\/stftframe\/phase","title":"var phase: [Float]","type":"property"}],"path":"\/documentation\/metalfft\/stftframe","title":"STFTFrame","type":"struct"},{"title":"Enumerations","type":"groupMarker"},{"children":[{"title":"Enumeration Cases","type":"groupMarker"},{"path":"\/documentation\/metalfft\/ffterror\/batchinputsize(expected:got:batchindex:)","title":"case batchInputSize(expected: Int, got: Int, batchIndex: Int)","type":"case"},{"path":"\/documentation\/metalfft\/ffterror\/bufferallocationfailed","title":"case bufferAllocationFailed","type":"case"},{"path":"\/documentation\/metalfft\/ffterror\/commandbufferfailed(_:)","title":"case commandBufferFailed(String)","type":"case"},{"path":"\/documentation\/metalfft\/ffterror\/invalidinputsize(expected:got:)","title":"case invalidInputSize(expected: Int, got: Int)","type":"case"},{"path":"\/documentation\/metalfft\/ffterror\/kernelnotfound(_:)","title":"case kernelNotFound(String)","type":"case"},{"path":"\/documentation\/metalfft\/ffterror\/librarybuildfailed(_:)","title":"case libraryBuildFailed(any Error)","type":"case"},{"path":"\/documentation\/metalfft\/ffterror\/nocommandqueue","title":"case noCommandQueue","type":"case"},{"path":"\/documentation\/metalfft\/ffterror\/nometaldevice","title":"case noMetalDevice","type":"case"},{"path":"\/documentation\/metalfft\/ffterror\/unsupportedfftsize(_:)","title":"case unsupportedFFTSize(Int)","type":"case"},{"title":"Instance Properties","type":"groupMarker"},{"path":"\/documentation\/metalfft\/ffterror\/description","title":"var description: String","type":"property"},{"title":"Default Implementations","type":"groupMarker"},{"children":[{"title":"Instance Properties","type":"groupMarker"},{"path":"\/documentation\/metalfft\/ffterror\/localizeddescription","title":"var localizedDescription: String","type":"property"}],"path":"\/documentation\/metalfft\/ffterror\/error-implementations","title":"Error Implementations","type":"symbol"}],"path":"\/documentation\/metalfft\/ffterror","title":"FFTError","type":"enum"},{"children":[{"title":"Type Properties","type":"groupMarker"},{"path":"\/documentation\/metalfft\/octavebands\/centerfrequencies","title":"static let centerFrequencies: [Double]","type":"property"},{"title":"Type Methods","type":"groupMarker"},{"path":"\/documentation\/metalfft\/octavebands\/analyze(magnitudes:samplerate:fftsize:)","title":"static func analyze(magnitudes: [Float], sampleRate: Double, fftSize: Int) -> [(center: Double, energy: Float)]","type":"method"},{"path":"\/documentation\/metalfft\/octavebands\/energies(magnitudes:samplerate:fftsize:)","title":"static func energies(magnitudes: [Float], sampleRate: Double, fftSize: Int) -> [Float]","type":"method"}],"path":"\/documentation\/metalfft\/octavebands","title":"OctaveBands","type":"enum"},{"children":[{"title":"Type Methods","type":"groupMarker"},{"path":"\/documentation\/metalfft\/psd\/coherence(a:b:fftsize:hopsize:samplerate:window:)","title":"static func coherence(a: [Float], b: [Float], fftSize: Int, hopSize: Int, sampleRate: Double, window: WindowType) throws -> [Float]","type":"method"},{"path":"\/documentation\/metalfft\/psd\/crossspectral(channels:fftsize:hopsize:samplerate:window:)","title":"static func crossSpectral(channels: [[Float]], fftSize: Int, hopSize: Int, sampleRate: Double, window: WindowType) throws -> CrossSpectralResult","type":"method"},{"path":"\/documentation\/metalfft\/psd\/welch(signal:fftsize:hopsize:samplerate:window:)","title":"static func welch(signal: [Float], fftSize: Int, hopSize: Int, sampleRate: Double, window: WindowType) throws -> [Float]","type":"method"}],"path":"\/documentation\/metalfft\/psd","title":"PSD","type":"enum"},{"children":[{"title":"Type Methods","type":"groupMarker"},{"path":"\/documentation\/metalfft\/peakdetection\/fundamentalfrequency(magnitudes:samplerate:fftsize:minfreq:maxfreq:magnitudethreshold:)","title":"static func fundamentalFrequency(magnitudes: [Float], sampleRate: Double, fftSize: Int, minFreq: Double, maxFreq: Double, magnitudeThreshold: Float) -> (index: Int, rawFrequency: Double)?","type":"method"},{"path":"\/documentation\/metalfft\/peakdetection\/parabolicinterpolation(magnitudes:peakindex:samplerate:fftsize:)","title":"static func parabolicInterpolation(magnitudes: [Float], peakIndex: Int, sampleRate: Double, fftSize: Int) -> Double","type":"method"},{"path":"\/documentation\/metalfft\/peakdetection\/peak(in:range:)","title":"static func peak(in: [Float], range: Range<Int>?) -> (index: Int, value: Float)?","type":"method"},{"path":"\/documentation\/metalfft\/peakdetection\/toppeaks(in:count:minspacing:)","title":"static func topPeaks(in: [Float], count: Int, minSpacing: Int) -> [(index: Int, value: Float)]","type":"method"}],"path":"\/documentation\/metalfft\/peakdetection","title":"PeakDetection","type":"enum"},{"children":[{"title":"Type Properties","type":"groupMarker"},{"path":"\/documentation\/metalfft\/pitch\/notenames","title":"static let noteNames: [String]","type":"property"},{"title":"Type Methods","type":"groupMarker"},{"path":"\/documentation\/metalfft\/pitch\/centsdeviation(frequency:referencea:)","title":"static func centsDeviation(frequency: Float, referenceA: Float) -> Float?","type":"method"},{"path":"\/documentation\/metalfft\/pitch\/frequency(midinote:referencea:)","title":"static func frequency(midiNote: Int, referenceA: Float) -> Float","type":"method"},{"path":"\/documentation\/metalfft\/pitch\/midinote(frequency:referencea:)","title":"static func midiNote(frequency: Float, referenceA: Float) -> Int?","type":"method"},{"path":"\/documentation\/metalfft\/pitch\/midinotes(frequencies:referencea:)","title":"static func midiNotes(frequencies: [Float], referenceA: Float) -> [Int?]","type":"method"},{"path":"\/documentation\/metalfft\/pitch\/note(frequency:referencea:)","title":"static func note(frequency: Float, referenceA: Float) -> (name: String, octave: Int)?","type":"method"}],"path":"\/documentation\/metalfft\/pitch","title":"Pitch","type":"enum"},{"children":[{"title":"Structures","type":"groupMarker"},{"children":[{"title":"Initializers","type":"groupMarker"},{"path":"\/documentation\/metalfft\/spectrum\/noiseconfig\/init(lowfreqdominancethreshold:flatnessvariancethreshold:peaktomeanratiothreshold:)","title":"init(lowFreqDominanceThreshold: Float, flatnessVarianceThreshold: Float, peakToMeanRatioThreshold: Float)","type":"init"},{"title":"Instance Properties","type":"groupMarker"},{"path":"\/documentation\/metalfft\/spectrum\/noiseconfig\/flatnessvariancethreshold","title":"var flatnessVarianceThreshold: Float","type":"property"},{"path":"\/documentation\/metalfft\/spectrum\/noiseconfig\/lowfreqdominancethreshold","title":"var lowFreqDominanceThreshold: Float","type":"property"},{"path":"\/documentation\/metalfft\/spectrum\/noiseconfig\/peaktomeanratiothreshold","title":"var peakToMeanRatioThreshold: Float","type":"property"},{"title":"Type Properties","type":"groupMarker"},{"path":"\/documentation\/metalfft\/spectrum\/noiseconfig\/default","title":"static let `default`: Spectrum.NoiseConfig","type":"property"}],"path":"\/documentation\/metalfft\/spectrum\/noiseconfig","title":"Spectrum.NoiseConfig","type":"struct"},{"title":"Type Methods","type":"groupMarker"},{"path":"\/documentation\/metalfft\/spectrum\/isnoise(_:samplerate:fftsize:config:)","title":"static func isNoise([Float], sampleRate: Double, fftSize: Int, config: Spectrum.NoiseConfig) -> Bool","type":"method"},{"path":"\/documentation\/metalfft\/spectrum\/magnitudes(_:count:)","title":"static func magnitudes([SIMD2<Float>], count: Int?) -> [Float]","type":"method"},{"path":"\/documentation\/metalfft\/spectrum\/normalize(_:)","title":"static func normalize(inout [Float])","type":"method"},{"path":"\/documentation\/metalfft\/spectrum\/phase(_:)","title":"static func phase([SIMD2<Float>]) -> [Float]","type":"method"},{"path":"\/documentation\/metalfft\/spectrum\/rms(_:)-9bgbv","title":"static func rms([Float]) -> Float","type":"method"},{"path":"\/documentation\/metalfft\/spectrum\/rms(_:)-9rrya","title":"static func rms(UnsafeBufferPointer<Float>) -> Float","type":"method"},{"path":"\/documentation\/metalfft\/spectrum\/todecibels(_:floordb:)","title":"static func toDecibels([Float], floorDB: Float) -> [Float]","type":"method"}],"path":"\/documentation\/metalfft\/spectrum","title":"Spectrum","type":"enum"},{"children":[{"title":"Type Methods","type":"groupMarker"},{"path":"\/documentation\/metalfft\/window\/apply(_:input:output:)","title":"static func apply([Float], input: UnsafeBufferPointer<Float>, output: inout [Float])","type":"method"},{"path":"\/documentation\/metalfft\/window\/apply(_:to:)","title":"static func apply([Float], to: [Float]) -> [Float]","type":"method"},{"path":"\/documentation\/metalfft\/window\/blackman(_:)","title":"static func blackman(Int) -> [Float]","type":"method"},{"path":"\/documentation\/metalfft\/window\/flattop(_:)","title":"static func flatTop(Int) -> [Float]","type":"method"},{"path":"\/documentation\/metalfft\/window\/hamming(_:)","title":"static func hamming(Int) -> [Float]","type":"method"},{"path":"\/documentation\/metalfft\/window\/hann(_:)","title":"static func hann(Int) -> [Float]","type":"method"},{"path":"\/documentation\/metalfft\/window\/kaiser(_:beta:)","title":"static func kaiser(Int, beta: Double) -> [Float]","type":"method"}],"path":"\/documentation\/metalfft\/window","title":"Window","type":"enum"},{"children":[{"title":"Enumeration Cases","type":"groupMarker"},{"path":"\/documentation\/metalfft\/windowtype\/blackman","title":"case blackman","type":"case"},{"path":"\/documentation\/metalfft\/windowtype\/flattop","title":"case flatTop","type":"case"},{"path":"\/documentation\/metalfft\/windowtype\/hamming","title":"case hamming","type":"case"},{"path":"\/documentation\/metalfft\/windowtype\/hann","title":"case hann","type":"case"},{"path":"\/documentation\/metalfft\/windowtype\/kaiser(beta:)","title":"case kaiser(beta: Double)","type":"case"},{"path":"\/documentation\/metalfft\/windowtype\/rectangular","title":"case rectangular","type":"case"},{"title":"Instance Methods","type":"groupMarker"},{"path":"\/documentation\/metalfft\/windowtype\/coefficients(_:)","title":"func coefficients(Int) -> [Float]","type":"method"}],"path":"\/documentation\/metalfft\/windowtype","title":"WindowType","type":"enum"}],"path":"\/documentation\/metalfft","title":"MetalFFT","type":"module"}]},"schemaVersion":{"major":0,"minor":1,"patch":2}}